LICENSE
MANIFEST.in
README.md
setup.py
wg_system/__init__.py
wg_system/__version__.py
wg_system.egg-info/PKG-INFO
wg_system.egg-info/SOURCES.txt
wg_system.egg-info/dependency_links.txt
wg_system.egg-info/requires.txt
wg_system.egg-info/top_level.txt
wg_system/registration/__init__.py
wg_system/registration/application.py
wg_system/registration/endpoints.py
wg_system/registration/models.py
wg_system/registration/resources.py
wg_system/registration/routes.py
wg_system/registration/schemas.py
wg_system/registration/settings.py
wg_system/utils/__init__.py
wg_system/utils/recaptcha.py